{
  "contact_types": {
    "military": {
      "name": "Militaire",
      "desc": "Contact avec les forces armées"
    },
    "merchant": {
      "name": "Marchand",
      "desc": "Contact commercial"
    },
    "underworld": {
      "name": "Pègre",
      "desc": "Contact avec le marché noir"
    },
    "diplomatic": {
      "name": "Diplomatique",
      "desc": "Contact politique"
    }
  },
  "relationship_levels": {
    "hostile": "Hostile",
    "suspicious": "Méfiant",
    "neutral": "Neutre",
    "favorable": "Favorable",
    "friendly": "Amical",
    "cooperative": "Coopératif"
  }
}
