[
  {
    "csv_row": 9257,
    "id": "sdtuMercReactStronger",
    "column": "options",
    "option_line": "cutCommLinkNoText:Couper la comm",
    "original": "Couper la comm",
    "translated": "Couper la comm"
  },
  {
    "csv_row": 9262,
    "id": "sdtuMercHegReact1onMyWay",
    "column": "options",
    "option_line": "cutCommLink:Couper la comm",
    "original": "Couper la comm",
    "translated": "Couper la comm"
  },
  {
    "csv_row": 9267,
    "id": "sdtuMercGreetingGotDebris",
    "column": "options",
    "option_line": "cutCommLink:Couper la comm",
    "original": "Couper la comm",
    "translated": "Couper la comm"
  },
  {
    "csv_row": 9279,
    "id": "sdtuNewsEndYourDoing",
    "column": "text",
    "original": "\"Vous me blessez par cette accusation, capitaine,\" dit Macario avec une pointe d'amusement glacial.",
    "translated": ""
  },
  {
    "csv_row": 9285,
    "id": "sdtuReturnNewsEnd",
    "column": "options",
    "option_line": "sdtu_returnNewsEnd2:Couper la comm",
    "original": "Couper la comm",
    "translated": "Couper la comm"
  },
  {
    "csv_row": 9293,
    "id": "anhCantinaAskStartCap",
    "column": "options",
    "option_line": "anh_cantinaReturn:Retourner au bar",
    "original": "Retourner au bar",
    "translated": ""
  },
  {
    "csv_row": 9309,
    "id": "anhCantinaDontLookTerrorists",
    "column": "text",
    "original": "Le sourire du vieil homme revient, comme s'il s'attendait a ce que vous disiez cela.",
    "translated": ""
  },
  {
    "csv_row": 9311,
    "id": "anhCantinaFeelings",
    "column": "options",
    "option_line": "anh_cantinaAskFeelings2:\"Je suppose que oui.\"",
    "original": "Je suppose que oui.",
    "translated": ""
  },
  {
    "csv_row": 9321,
    "id": "anhCantinaAccept",
    "column": "options",
    "option_line": "anh_cantinaReturn:Retourner au bar",
    "original": "Retourner au bar",
    "translated": ""
  },
  {
    "csv_row": 9329,
    "id": "anhDiktatPatrolStall2",
    "column": "options",
    "option_line": "anh_diktatPatrolStall3:\"Vous voulez bien m'expliquer ?\"",
    "original": "Vous voulez bien m'expliquer ?",
    "translated": ""
  }
]